Metadata-Version: 1.0
Name: ed-distributions
Version: 0.1
Summary: Gaussian distributions
Home-page: UNKNOWN
Author: Edie738
Author-email: dredielam@gmail.com
License: UNKNOWN
Platform: UNKNOWN
